LICENSE
giant_utils/__init__.py
giant_utils/apps.py
giant_utils/fields.py
giant_utils/format_bytes.py
giant_utils/sender.py
giant_utils/widgets.py
giant_utils-0.2.dist-info/LICENSE
giant_utils-0.2.dist-info/METADATA
giant_utils-0.2.dist-info/WHEEL
giant_utils-0.2.dist-info/RECORD
