Metadata-Version: 2.1
Name: giant-utils
Version: 0.2
Summary: A small reusable package that adds small commonly used functions to a project
Home-page: https://github.com/giantmade/giant-utils
License: MIT
Keywords: app
Author: Dominic-Chaple
Author-email: dominic.chaple@giantdigital.co.uk
Requires-Python: >3.7,<4
Classifier: Environment :: Console
Classifier: License :: OSI Approved :: MIT License
Classifier: Operating System :: OS Independent
Classifier: Programming Language :: Python :: 3
Classifier: Programming Language :: Python :: 3.8
Classifier: Programming Language :: Python :: 3.9
Classifier: Programming Language :: Python :: 3.10
Classifier: Programming Language :: Python :: 3.11
Classifier: Topic :: Software Development :: Documentation
Classifier: Topic :: Software Development :: Libraries :: Python Modules
Requires-Dist: dj-email-url (>=1.0.2,<2.0.0)
Requires-Dist: django (>=3.0)
Requires-Dist: django-cms (>=3,<4.0)
Project-URL: Repository, https://github.com/giantmade/giant-utils
